argos/__init__.py
argos/agent.py
argos/commands.py
argos/config-example.yaml
argos/logging.py
argos/checks/__init__.py
argos/checks/base.py
argos/checks/checks.py
argos/schemas/__init__.py
argos/schemas/config.py
argos/schemas/models.py
argos/schemas/utils.py
argos/server/__init__.py
argos/server/alerting.py
argos/server/exceptions.py
argos/server/main.py
argos/server/models.py
argos/server/queries.py
argos/server/settings.py
argos/server/migrations/alembic.ini
argos/server/migrations/env.py
argos/server/migrations/script.py.mako
argos/server/migrations/versions/127d74c770bb_add_recheck_delay.py
argos/server/migrations/versions/1a3497f9f71b_adding_configcache_model.py
argos/server/migrations/versions/31255a412d63_add_form_data_to_tasks.py
argos/server/migrations/versions/5f6cb30db996_add_job_queue.py
argos/server/migrations/versions/64f73a79b7d8_add_ip_version_to_checks.py
argos/server/migrations/versions/7d480e6f1112_initial_migrations.py
argos/server/migrations/versions/80a29f64f91c_add_retries_before_notification_feature.py
argos/server/migrations/versions/8b58ced14d6e_add_task_index.py
argos/server/migrations/versions/a1e98cf72a5c_make_frequency_a_float.py
argos/server/migrations/versions/bd4b4962696a_use_bigint_for_results_id_field.py
argos/server/migrations/versions/c780864dc407_add_users_table.py
argos/server/migrations/versions/dcf73fa19fce_specify_check_method.py
argos/server/migrations/versions/defda3f2952d_add_on_delete_cascade_to_results_task_id.py
argos/server/migrations/versions/e99bc35702c9_add_severity_to_task_and_add_severity_.py
argos/server/routes/__init__.py
argos/server/routes/api.py
argos/server/routes/dependencies.py
argos/server/routes/views.py
argos/server/static/logo-64.png
argos/server/static/logo.png
argos/server/static/pico.min.css
argos/server/static/styles.css
argos/server/templates/agents.html
argos/server/templates/base.html
argos/server/templates/domain.html
argos/server/templates/domains.html
argos/server/templates/index.html
argos_monitoring-0.9.0.dist-info/METADATA
argos_monitoring-0.9.0.dist-info/WHEEL
argos_monitoring-0.9.0.dist-info/entry_points.txt
argos_monitoring-0.9.0.dist-info/licenses/LICENSE
argos_monitoring-0.9.0.dist-info/RECORD
