Metadata-Version: 2.4
Name: argos-monitoring
Version: 0.9.0
Summary: Distributed supervision tool for HTTP.
Project-URL: homepage, https://argos-monitoring.framasoft.org/
Project-URL: repository, https://framagit.org/framasoft/framaspace/argos
Project-URL: Funding, https://framasoft.org/en/#support
Project-URL: Tracker, https://framagit.org/framasoft/framaspace/argos/-/issues
Author-email: Alexis Métaireau <alexis@notmyidea.org>, Luc Didry <luc+argos@framasoft.org>
License-File: LICENSE
Classifier: Intended Audience :: System Administrators
Classifier: License :: OSI Approved :: GNU Affero General Public License v3 or later (AGPLv3+)
Classifier: Programming Language :: Python :: 3.11
Classifier: Programming Language :: Python :: 3.12
Classifier: Topic :: Internet :: WWW/HTTP
Classifier: Topic :: Internet :: WWW/HTTP :: WSGI :: Application
Requires-Dist: alembic<1.14,>=1.13.0
Requires-Dist: apprise<2,>=1.9.0
Requires-Dist: bcrypt<5,>=4.1.3
Requires-Dist: click<9,>=8.1
Requires-Dist: durations-nlp<2,>=1.0.1
Requires-Dist: fastapi-login<2,>=1.10.0
Requires-Dist: fastapi-utils<0.9,>=0.8.0
Requires-Dist: fastapi<0.104,>=0.103
Requires-Dist: httpx<0.28.0,>=0.27.2
Requires-Dist: jinja2<4,>=3.0
Requires-Dist: jsonpointer<4,>=3.0
Requires-Dist: passlib<2,>=1.7.4
Requires-Dist: psutil<6,>=5.9.8
Requires-Dist: psycopg2-binary<3,>=2.9
Requires-Dist: pydantic-settings<3,>=2.0
Requires-Dist: pydantic[email]<3,>=2.4
Requires-Dist: python-multipart<1,>=0.0.9
Requires-Dist: pyyaml-include<2,>=1.3
Requires-Dist: pyyaml<7,>=6.0
Requires-Dist: sqlalchemy-utils<1,>=0.41
Requires-Dist: sqlalchemy[asyncio]<3,>=2.0
Requires-Dist: tenacity<9,>=8.2
Requires-Dist: typing-inspect<1,>=0.9.0
Requires-Dist: uvicorn<1,>=0.23
Provides-Extra: dev
Requires-Dist: black==23.3.0; extra == 'dev'
Requires-Dist: djlint>=1.34.0; extra == 'dev'
Requires-Dist: hatch==1.13.0; extra == 'dev'
Requires-Dist: ipdb<0.14,>=0.13; extra == 'dev'
Requires-Dist: ipython<9,>=8.16; extra == 'dev'
Requires-Dist: isort==5.11.5; extra == 'dev'
Requires-Dist: mypy<2,>=1.10.0; extra == 'dev'
Requires-Dist: pylint>=3.2.5; extra == 'dev'
Requires-Dist: pytest-asyncio<1,>=0.21; extra == 'dev'
Requires-Dist: pytest>=6.2.5; extra == 'dev'
Requires-Dist: respx<1,>=0.20; extra == 'dev'
Requires-Dist: ruff<1,==0.1.5; extra == 'dev'
Requires-Dist: sphinx-autobuild; extra == 'dev'
Requires-Dist: types-pyyaml; extra == 'dev'
Provides-Extra: docs
Requires-Dist: cogapp; extra == 'docs'
Requires-Dist: myst-parser<3,>=2.0; extra == 'docs'
Requires-Dist: shibuya; extra == 'docs'
Requires-Dist: sphinx-design; extra == 'docs'
Requires-Dist: sphinx<8,>=7; extra == 'docs'
Requires-Dist: sphinxcontrib-mermaid<1,>=0.9; extra == 'docs'
Provides-Extra: gunicorn
Requires-Dist: gunicorn<22,>=21.2; extra == 'gunicorn'
Provides-Extra: ldap
Requires-Dist: python-ldap<4,>=3.4.4; extra == 'ldap'
